[
  {
      "grouping":"Architecture",
      "skills":[ "RESTful APIs","SaaS/PaaS/IaaS"]
  },{
      "grouping":"Languages, Operating Systems & Tools",
      "skills":[ "Java","Python", "C++", "C", "Ruby", "JavaScript", "React", "HTML", "CSS", "git", "linux","bash","jquery", "node.js", "npm", "yarn", "webpack"]
  },
  {
      "grouping":"Platform Development & Administration",
      "skills":[ "MySQL","Wordpress", "Hugo"]
  },
  {
      "grouping":"Data Management",
      "skills":[
        {"name": "Supabase", "icon": "supabase"},
        "PostgreSQL",
        "SQLite"
      ]
  }
]
